[
  {
    "topicId": "design-principles",
    "topicName": "Design Principles",
    "contentPath": "learn/design-principles/design-principles.json"
  },
  {
    "topicId": "design-patterns",
    "topicName": "Design Patterns",
    "contentPath": "learn/design-principles/design-principles.json"
  },
  {
    "topicId": "microservices",
    "topicName": "Microservices",
    "contentPath": "learn/design-patterns/design-patterns.json"
  },
  {
    "topicId": "spring-boot",
    "topicName": "Spring Boot",
    "contentPath": "learn/spring-boot/spring-boot.json"
  },
  {
    "topicId": "spring-cloud",
    "topicName": "Spring Cloud",
    "contentPath": "learn/spring-cloud/spring-cloud.json"
  },
  {
    "topicId": "docker",
    "topicName": "Docker",
    "contentPath": "learn/docker/docker.json"
  }
]
